number2bangla_word_text/__init__.py
number2bangla_word_text/number2banglaword.py
number2bangla_word_text-0.0.4.dist-info/LICENSE
number2bangla_word_text-0.0.4.dist-info/METADATA
number2bangla_word_text-0.0.4.dist-info/WHEEL
number2bangla_word_text-0.0.4.dist-info/top_level.txt
number2bangla_word_text-0.0.4.dist-info/RECORD
