Metadata-Version: 2.1
Name: number2bangla-word-text
Version: 0.0.4
Summary: Convert Number to Bangla Word Text
Home-page: https://github.com/MdNazmul9/number2bangla_word_text
Author: Md. Nazmul Hossain
Author-email: <nazmul.cse48@gmail.com>
License: UNKNOWN
Keywords: python3,number2bangali-word-text,number2word-text,number-to-bangali-word-text,number-to-word-text,number-to-bangla-text
Platform: UNKNOWN
Classifier: Development Status :: 1 - Planning
Classifier: Intended Audience :: Developers
Classifier: Programming Language :: Python :: 3
Classifier: License :: OSI Approved :: MIT License
Classifier: Operating System :: OS Independent
